{"nodes": [{"id": "dnn_pitchdnn_layers_file", "label": "dnn_pitchdnn_layers.rs", "file_type": "code", "source_file": "/home/ct37/projects/opus-rust/crates/opus/tests/dnn_pitchdnn_layers.rs", "source_location": null, "source_url": null, "captured_at": null, "author": null, "contributor": null}, {"id": "concept_rcp_ps_divergence", "label": "C SSE2 _mm_rcp_ps reciprocal approximation causes per-element ~2e-4 divergence in tanh/sigmoid; accumulates to ~0.34 across PitchDNN dense layers", "file_type": "code", "source_file": "/home/ct37/projects/opus-rust/crates/opus/tests/dnn_pitchdnn_layers.rs", "source_location": null, "source_url": null, "captured_at": null, "author": null, "contributor": null}], "edges": [{"source": "dnn_pitchdnn_layers_file", "target": "common_mod_file", "relation": "references", "confidence": "EXTRACTED", "confidence_score": 1.0, "source_file": "/home/ct37/projects/opus-rust/crates/opus/tests/dnn_pitchdnn_layers.rs", "source_location": null, "weight": 1.0}, {"source": "dnn_pitchdnn_layers_file", "target": "concept_rcp_ps_divergence", "relation": "implements", "confidence": "EXTRACTED", "confidence_score": 1.0, "source_file": "/home/ct37/projects/opus-rust/crates/opus/tests/dnn_pitchdnn_layers.rs", "source_location": null, "weight": 1.0}, {"source": "dnn_pitchdnn_layers_file", "target": "dnn_model_tests_file", "relation": "semantically_similar_to", "confidence": "INFERRED", "confidence_score": 0.85, "source_file": "/home/ct37/projects/opus-rust/crates/opus/tests/dnn_pitchdnn_layers.rs", "source_location": null, "weight": 1.0}, {"source": "dnn_pitchdnn_layers_file", "target": "dnn_nnet_tests_file", "relation": "semantically_similar_to", "confidence": "INFERRED", "confidence_score": 0.8, "source_file": "/home/ct37/projects/opus-rust/crates/opus/tests/dnn_pitchdnn_layers.rs", "source_location": null, "weight": 1.0}, {"source": "concept_rcp_ps_divergence", "target": "concept_silk_stereo_q13_drift", "relation": "conceptually_related_to", "confidence": "INFERRED", "confidence_score": 0.7, "source_file": "/home/ct37/projects/opus-rust/crates/opus/tests/dnn_pitchdnn_layers.rs", "source_location": null, "weight": 1.0}], "hyperedges": []}